pysentio/__init__.py
pysentio/const.py
pysentio-0.0.52.dist-info/LICENSE
pysentio-0.0.52.dist-info/METADATA
pysentio-0.0.52.dist-info/WHEEL
pysentio-0.0.52.dist-info/top_level.txt
pysentio-0.0.52.dist-info/RECORD
