Metadata-Version: 2.1
Name: pysentio
Version: 0.0.52
Summary: Python library for Sentio Pro Sauna Controller
Home-page: https://github.com/astrandb/pysentio
Author: Ake Strandberg
Author-email: ake@strandberg.eu
License: UNKNOWN
Platform: UNKNOWN
Classifier: Programming Language :: Python :: 3
Classifier: License :: OSI Approved :: MIT License
Classifier: Operating System :: OS Independent
Classifier: Development Status :: 4 - Beta
Requires-Python: >=3.8
License-File: LICENSE
Requires-Dist: pyserial (>=3.4)
